Metadata-Version: 2.1
Name: temp-gmail
Version: 1.0.1
Summary: temp gmail api.
Home-page: https://github.com/zukixa/temp-gmail
Author: zukixa
Author-email: 56563509+zukixa@users.noreply.github.com
Classifier: Programming Language :: Python :: 3
Classifier: License :: OSI Approved :: MIT License
Classifier: Operating System :: OS Independent
Requires-Python: >=3.6
Requires-Dist: curl_cffi
